{"nodes":[{"name":"FBXO34"},{"name":"TGFBR1"},{"name":"FBXO30"},{"name":"UBE2H"},{"name":"YTHDC2"},{"name":"MAP3K7"},{"name":"APC"},{"name":"RBX1"},{"name":"NRP1"},{"name":"TGFBR2"},{"name":"NOTCH1"},{"name":"PSEN1"},{"name":"IL6R"},{"name":"TMEM9B"},{"name":"FAAP100"},{"name":"CSF1R"},{"name":"KRAS"},{"name":"SBF1"},{"name":"GBF1"},{"name":"KIF14"},{"name":"XRN1"},{"name":"WWP2"},{"name":"ZNF550"},{"name":"CLASP2"},{"name":"DMXL1"},{"name":"CIP2A"},{"name":"PIP4K2A"},{"name":"WDR26"},{"name":"TAB2"},{"name":"RIOK3"},{"name":"TRIM23"},{"name":"MARCHF8"},{"name":"HBP1"},{"name":"GSK3B"},{"name":"UBR2"},{"name":"TXNL1"},{"name":"LACTB2"},{"name":"CREBBP"},{"name":"RNF103"},{"name":"KIF5B"},{"name":"CHUK"},{"name":"YWHAH"},{"name":"TAB1"},{"name":"FKBP5"},{"name":"USP9X"},{"name":"TAB3"},{"name":"CUL4B"},{"name":"ERBIN"},{"name":"HOOK3"},{"name":"CCDC6"},{"name":"CFH"}],"edges":[{"source":"FBXO34","target":"TGFBR1"},{"source":"TGFBR1","target":"TGFBR2"},{"source":"TGFBR1","target":"TMEM9B"},{"source":"FBXO30","target":"MAP3K7"},{"source":"FBXO30","target":"FBXO34"},{"source":"FBXO30","target":"YTHDC2"},{"source":"FBXO30","target":"RBX1"},{"source":"FBXO30","target":"UBE2H"},{"source":"UBE2H","target":"UBR2"},{"source":"UBE2H","target":"WDR26"},{"source":"YTHDC2","target":"ZNF550"},{"source":"MAP3K7","target":"TAB1"},{"source":"MAP3K7","target":"TAB2"},{"source":"MAP3K7","target":"YWHAH"},{"source":"MAP3K7","target":"USP9X"},{"source":"MAP3K7","target":"TAB3"},{"source":"APC","target":"CCDC6"},{"source":"APC","target":"CREBBP"},{"source":"APC","target":"KIF5B"},{"source":"APC","target":"GSK3B"},{"source":"APC","target":"HOOK3"},{"source":"APC","target":"FBXO30"},{"source":"APC","target":"ERBIN"},{"source":"NRP1","target":"TGFBR1"},{"source":"NOTCH1","target":"TGFBR1"},{"source":"NOTCH1","target":"SBF1"},{"source":"PSEN1","target":"TGFBR1"},{"source":"IL6R","target":"TGFBR1"},{"source":"FAAP100","target":"IL6R"},{"source":"CSF1R","target":"IL6R"},{"source":"KRAS","target":"UBE2H"},{"source":"KRAS","target":"PSEN1"},{"source":"SBF1","target":"TGFBR2"},{"source":"GBF1","target":"XRN1"},{"source":"GBF1","target":"YTHDC2"},{"source":"GBF1","target":"KIF5B"},{"source":"KIF14","target":"YTHDC2"},{"source":"XRN1","target":"YTHDC2"},{"source":"WWP2","target":"YTHDC2"},{"source":"CLASP2","target":"YTHDC2"},{"source":"DMXL1","target":"YTHDC2"},{"source":"CIP2A","target":"KIF14"},{"source":"CIP2A","target":"YTHDC2"},{"source":"CIP2A","target":"GBF1"},{"source":"PIP4K2A","target":"SBF1"},{"source":"PIP4K2A","target":"UBE2H"},{"source":"PIP4K2A","target":"WDR26"},{"source":"TAB2","target":"TAB3"},{"source":"RIOK3","target":"UBE2H"},{"source":"TRIM23","target":"UBE2H"},{"source":"MARCHF8","target":"UBE2H"},{"source":"HBP1","target":"UBE2H"},{"source":"GSK3B","target":"KIF5B"},{"source":"TXNL1","target":"UBE2H"},{"source":"LACTB2","target":"UBE2H"},{"source":"CREBBP","target":"HBP1"},{"source":"RNF103","target":"UBE2H"},{"source":"KIF5B","target":"YWHAH"},{"source":"CHUK","target":"MAP3K7"},{"source":"CHUK","target":"ERBIN"},{"source":"CHUK","target":"KIF5B"},{"source":"TAB1","target":"TAB2"},{"source":"FKBP5","target":"GSK3B"},{"source":"FKBP5","target":"MAP3K7"},{"source":"CUL4B","target":"MAP3K7"},{"source":"ERBIN","target":"KRAS"},{"source":"HOOK3","target":"KIF5B"},{"source":"CCDC6","target":"GSK3B"},{"source":"CCDC6","target":"KRAS"},{"source":"CFH","target":"NRP1"}]}