{"nodes":[{"name":"LPCAT3"},{"name":"RER1"},{"name":"SACM1L"},{"name":"ABHD16A"},{"name":"SYVN1"},{"name":"ALG11"},{"name":"MGST2"},{"name":"MBOAT1"},{"name":"LMF2"},{"name":"LEPROT"},{"name":"SLC66A2"},{"name":"SLC26A6"},{"name":"C3AR1"},{"name":"LMAN2"},{"name":"PTDSS1"},{"name":"KRTCAP2"},{"name":"IL2RA"},{"name":"VAPA"},{"name":"ATP2A2"},{"name":"RPN1"},{"name":"CCDC47"},{"name":"SSR1"},{"name":"DERL1"},{"name":"EMD"},{"name":"SLC35E3"},{"name":"MT-CO3"},{"name":"SPCS2"},{"name":"SEC61B"},{"name":"SEC62"},{"name":"ZMPSTE24"},{"name":"GPAA1"},{"name":"HM13"},{"name":"VAPB"},{"name":"SEC63"},{"name":"RPN2"},{"name":"YIPF5"},{"name":"LPGAT1"},{"name":"PREB"},{"name":"GDE1"},{"name":"RNF170"},{"name":"EMC7"},{"name":"RNF185"},{"name":"ERLIN2"},{"name":"STX8"},{"name":"SEC61A1"},{"name":"VAMP3"},{"name":"EI24"},{"name":"TSPO"},{"name":"TP53"},{"name":"AK2"},{"name":"TMX3"}],"edges":[{"source":"LPCAT3","target":"SLC26A6"},{"source":"LPCAT3","target":"MGST2"},{"source":"LPCAT3","target":"PTDSS1"},{"source":"LPCAT3","target":"RER1"},{"source":"LPCAT3","target":"SACM1L"},{"source":"LPCAT3","target":"MBOAT1"},{"source":"LPCAT3","target":"SLC66A2"},{"source":"LPCAT3","target":"SYVN1"},{"source":"RER1","target":"SEC62"},{"source":"RER1","target":"SEC61A1"},{"source":"RER1","target":"SPCS2"},{"source":"RER1","target":"SYVN1"},{"source":"RER1","target":"SSR1"},{"source":"RER1","target":"ZMPSTE24"},{"source":"RER1","target":"SLC66A2"},{"source":"SACM1L","target":"VAPB"},{"source":"SACM1L","target":"VAPA"},{"source":"SACM1L","target":"SPCS2"},{"source":"ABHD16A","target":"MGST2"},{"source":"ABHD16A","target":"LPCAT3"},{"source":"ABHD16A","target":"PREB"},{"source":"ABHD16A","target":"HM13"},{"source":"ABHD16A","target":"CCDC47"},{"source":"ALG11","target":"ZMPSTE24"},{"source":"ALG11","target":"ATP2A2"},{"source":"ALG11","target":"RPN1"},{"source":"ALG11","target":"VAPB"},{"source":"ALG11","target":"TMX3"},{"source":"ALG11","target":"CCDC47"},{"source":"ALG11","target":"SACM1L"},{"source":"ALG11","target":"LPCAT3"},{"source":"MGST2","target":"STX8"},{"source":"MGST2","target":"RNF170"},{"source":"MGST2","target":"VAMP3"},{"source":"MGST2","target":"TP53"},{"source":"MBOAT1","target":"SACM1L"},{"source":"MBOAT1","target":"YIPF5"},{"source":"LMF2","target":"SSR1"},{"source":"LMF2","target":"SEC62"},{"source":"LMF2","target":"LPCAT3"},{"source":"LMF2","target":"SYVN1"},{"source":"LMF2","target":"RPN1"},{"source":"LMF2","target":"SEC61A1"},{"source":"LMF2","target":"SEC61B"},{"source":"LMF2","target":"RNF185"},{"source":"LMF2","target":"RPN2"},{"source":"LMF2","target":"RER1"},{"source":"LMF2","target":"SPCS2"},{"source":"LEPROT","target":"TSPO"},{"source":"LEPROT","target":"LPCAT3"},{"source":"SLC66A2","target":"VAPA"},{"source":"C3AR1","target":"LPCAT3"},{"source":"LMAN2","target":"SEC61B"},{"source":"LMAN2","target":"PREB"},{"source":"LMAN2","target":"SSR1"},{"source":"LMAN2","target":"VAPA"},{"source":"LMAN2","target":"SPCS2"},{"source":"LMAN2","target":"SEC63"},{"source":"LMAN2","target":"LPCAT3"},{"source":"PTDSS1","target":"SEC62"},{"source":"PTDSS1","target":"SEC61B"},{"source":"PTDSS1","target":"SSR1"},{"source":"PTDSS1","target":"RPN1"},{"source":"PTDSS1","target":"SEC63"},{"source":"PTDSS1","target":"RPN2"},{"source":"KRTCAP2","target":"SSR1"},{"source":"KRTCAP2","target":"RPN2"},{"source":"KRTCAP2","target":"RPN1"},{"source":"KRTCAP2","target":"SEC63"},{"source":"KRTCAP2","target":"TMX3"},{"source":"KRTCAP2","target":"LPCAT3"},{"source":"KRTCAP2","target":"ZMPSTE24"},{"source":"IL2RA","target":"LPCAT3"},{"source":"VAPA","target":"VAPB"},{"source":"VAPA","target":"YIPF5"},{"source":"ATP2A2","target":"DERL1"},{"source":"ATP2A2","target":"SEC63"},{"source":"ATP2A2","target":"SPCS2"},{"source":"ATP2A2","target":"SSR1"},{"source":"ATP2A2","target":"SEC62"},{"source":"ATP2A2","target":"SEC61A1"},{"source":"ATP2A2","target":"CCDC47"},{"source":"ATP2A2","target":"MBOAT1"},{"source":"ATP2A2","target":"HM13"},{"source":"ATP2A2","target":"RPN2"},{"source":"ATP2A2","target":"SEC61B"},{"source":"ATP2A2","target":"VAPA"},{"source":"ATP2A2","target":"ZMPSTE24"},{"source":"ATP2A2","target":"EMD"},{"source":"ATP2A2","target":"EMC7"},{"source":"ATP2A2","target":"RNF185"},{"source":"ATP2A2","target":"RER1"},{"source":"ATP2A2","target":"VAPB"},{"source":"RPN1","target":"RPN2"},{"source":"RPN1","target":"SPCS2"},{"source":"RPN1","target":"SSR1"},{"source":"RPN1","target":"ZMPSTE24"},{"source":"RPN1","target":"SEC61B"},{"source":"RPN1","target":"SEC63"},{"source":"RPN1","target":"SEC61A1"},{"source":"RPN1","target":"SEC62"},{"source":"RPN1","target":"SYVN1"},{"source":"RPN1","target":"VAPA"},{"source":"CCDC47","target":"SEC63"},{"source":"CCDC47","target":"RPN1"},{"source":"CCDC47","target":"SSR1"},{"source":"CCDC47","target":"ZMPSTE24"},{"source":"CCDC47","target":"EMC7"},{"source":"CCDC47","target":"RPN2"},{"source":"CCDC47","target":"SEC61B"},{"source":"CCDC47","target":"SYVN1"},{"source":"CCDC47","target":"SPCS2"},{"source":"CCDC47","target":"SEC62"},{"source":"CCDC47","target":"SEC61A1"},{"source":"CCDC47","target":"DERL1"},{"source":"CCDC47","target":"KRTCAP2"},{"source":"CCDC47","target":"VAPA"},{"source":"CCDC47","target":"ERLIN2"},{"source":"CCDC47","target":"TMX3"},{"source":"CCDC47","target":"PREB"},{"source":"SSR1","target":"VAPA"},{"source":"SSR1","target":"VAPB"},{"source":"SSR1","target":"ZMPSTE24"},{"source":"SSR1","target":"TMX3"},{"source":"DERL1","target":"HM13"},{"source":"DERL1","target":"SPCS2"},{"source":"DERL1","target":"SEC61A1"},{"source":"DERL1","target":"SEC61B"},{"source":"DERL1","target":"SEC63"},{"source":"DERL1","target":"EMC7"},{"source":"DERL1","target":"SYVN1"},{"source":"DERL1","target":"VAPB"},{"source":"DERL1","target":"GDE1"},{"source":"DERL1","target":"RPN1"},{"source":"DERL1","target":"SSR1"},{"source":"DERL1","target":"TMX3"},{"source":"DERL1","target":"VAPA"},{"source":"DERL1","target":"MBOAT1"},{"source":"DERL1","target":"RNF185"},{"source":"DERL1","target":"PREB"},{"source":"DERL1","target":"EMD"},{"source":"EMD","target":"LMF2"},{"source":"EMD","target":"VAPB"},{"source":"EMD","target":"HM13"},{"source":"EMD","target":"PREB"},{"source":"EMD","target":"VAPA"},{"source":"EMD","target":"RNF185"},{"source":"EMD","target":"SYVN1"},{"source":"EMD","target":"MBOAT1"},{"source":"EMD","target":"SEC61B"},{"source":"SLC35E3","target":"SLC66A2"},{"source":"MT-CO3","target":"SLC66A2"},{"source":"SPCS2","target":"SSR1"},{"source":"SPCS2","target":"SYVN1"},{"source":"SPCS2","target":"ZMPSTE24"},{"source":"SEC61B","target":"SPCS2"},{"source":"SEC61B","target":"SEC62"},{"source":"SEC61B","target":"ZMPSTE24"},{"source":"SEC61B","target":"SSR1"},{"source":"SEC61B","target":"SYVN1"},{"source":"SEC61B","target":"SEC63"},{"source":"SEC61B","target":"VAPA"},{"source":"SEC62","target":"ZMPSTE24"},{"source":"SEC62","target":"SPCS2"},{"source":"SEC62","target":"SEC63"},{"source":"SEC62","target":"SSR1"},{"source":"SEC62","target":"VAPA"},{"source":"SEC62","target":"SYVN1"},{"source":"SEC62","target":"TMX3"},{"source":"GPAA1","target":"SEC61A1"},{"source":"GPAA1","target":"RER1"},{"source":"GPAA1","target":"LEPROT"},{"source":"GPAA1","target":"VAPB"},{"source":"HM13","target":"SSR1"},{"source":"HM13","target":"SEC61A1"},{"source":"HM13","target":"SEC63"},{"source":"HM13","target":"SEC61B"},{"source":"HM13","target":"RPN1"},{"source":"HM13","target":"RER1"},{"source":"HM13","target":"SEC62"},{"source":"HM13","target":"RPN2"},{"source":"HM13","target":"LMF2"},{"source":"HM13","target":"SPCS2"},{"source":"HM13","target":"ZMPSTE24"},{"source":"SEC63","target":"SSR1"},{"source":"SEC63","target":"VAPA"},{"source":"SEC63","target":"VAPB"},{"source":"SEC63","target":"SYVN1"},{"source":"RPN2","target":"SSR1"},{"source":"RPN2","target":"SPCS2"},{"source":"RPN2","target":"ZMPSTE24"},{"source":"RPN2","target":"SEC63"},{"source":"RPN2","target":"TMX3"},{"source":"RPN2","target":"SEC61B"},{"source":"RPN2","target":"VAPA"},{"source":"RPN2","target":"SEC62"},{"source":"LPGAT1","target":"MBOAT1"},{"source":"LPGAT1","target":"VAPA"},{"source":"PREB","target":"SSR1"},{"source":"PREB","target":"RPN1"},{"source":"PREB","target":"SEC63"},{"source":"PREB","target":"RPN2"},{"source":"PREB","target":"SEC61B"},{"source":"PREB","target":"SEC62"},{"source":"PREB","target":"SYVN1"},{"source":"GDE1","target":"SYVN1"},{"source":"GDE1","target":"LEPROT"},{"source":"GDE1","target":"VAPB"},{"source":"GDE1","target":"SEC61A1"},{"source":"RNF170","target":"TMX3"},{"source":"RNF170","target":"RNF185"},{"source":"EMC7","target":"RPN2"},{"source":"EMC7","target":"RPN1"},{"source":"EMC7","target":"SEC61A1"},{"source":"EMC7","target":"SSR1"},{"source":"EMC7","target":"SEC63"},{"source":"EMC7","target":"TMX3"},{"source":"EMC7","target":"SEC62"},{"source":"EMC7","target":"RER1"},{"source":"EMC7","target":"SEC61B"},{"source":"EMC7","target":"ZMPSTE24"},{"source":"EMC7","target":"SPCS2"},{"source":"EMC7","target":"KRTCAP2"},{"source":"EMC7","target":"LMAN2"},{"source":"EMC7","target":"HM13"},{"source":"EMC7","target":"PREB"},{"source":"RNF185","target":"SACM1L"},{"source":"RNF185","target":"RPN1"},{"source":"RNF185","target":"SEC61B"},{"source":"RNF185","target":"SYVN1"},{"source":"ERLIN2","target":"RNF170"},{"source":"ERLIN2","target":"MGST2"},{"source":"ERLIN2","target":"TSPO"},{"source":"SEC61A1","target":"SEC63"},{"source":"SEC61A1","target":"SPCS2"},{"source":"SEC61A1","target":"SEC61B"},{"source":"SEC61A1","target":"SSR1"},{"source":"SEC61A1","target":"SYVN1"},{"source":"SEC61A1","target":"ZMPSTE24"},{"source":"SEC61A1","target":"SEC62"},{"source":"EI24","target":"SEC61B"},{"source":"EI24","target":"MGST2"},{"source":"EI24","target":"EMD"},{"source":"AK2","target":"MGST2"},{"source":"TMX3","target":"VAPA"},{"source":"TMX3","target":"ZMPSTE24"}]}