{"nodes":[{"name":"SNX11"},{"name":"CCR1"},{"name":"GRB2"},{"name":"SPPL2A"},{"name":"ATP6V1C1"},{"name":"RP2"},{"name":"AP3B1"},{"name":"ATL3"},{"name":"DNAJC3"},{"name":"UBE2D1"},{"name":"LGALS8"},{"name":"EMP3"},{"name":"C18orf32"},{"name":"SLC9A6"},{"name":"B4GALT1"},{"name":"ZBTB7A"},{"name":"ARF6"},{"name":"XRCC4"},{"name":"ATG3"},{"name":"ATP6AP2"},{"name":"TRIM25"},{"name":"MOSPD2"},{"name":"YWHAZ"},{"name":"EEA1"},{"name":"SIRPA"},{"name":"SEC23B"},{"name":"KRAS"},{"name":"OSTF1"},{"name":"CLTA"},{"name":"ARF1"},{"name":"ATP6V0D1"},{"name":"AP3M1"},{"name":"CLTB"},{"name":"CAB39"},{"name":"EPB41L3"},{"name":"STAM2"},{"name":"NCF2"},{"name":"AP3D1"},{"name":"KIF5B"},{"name":"HDAC4"},{"name":"UEVLD"},{"name":"AP3S1"},{"name":"VTI1B"},{"name":"CLINT1"},{"name":"NAIP"},{"name":"CYRIB"},{"name":"PARP4"},{"name":"VASP"},{"name":"SNX17"},{"name":"PIP4K2C"},{"name":"KCTD12"}],"edges":[{"source":"SNX11","target":"SPPL2A"},{"source":"CCR1","target":"OSTF1"},{"source":"CCR1","target":"SIRPA"},{"source":"CCR1","target":"KCTD12"},{"source":"CCR1","target":"NCF2"},{"source":"CCR1","target":"SNX11"},{"source":"CCR1","target":"NAIP"},{"source":"GRB2","target":"OSTF1"},{"source":"GRB2","target":"VASP"},{"source":"GRB2","target":"TRIM25"},{"source":"GRB2","target":"SIRPA"},{"source":"GRB2","target":"YWHAZ"},{"source":"GRB2","target":"SEC23B"},{"source":"GRB2","target":"KRAS"},{"source":"GRB2","target":"SNX11"},{"source":"SPPL2A","target":"ZBTB7A"},{"source":"SPPL2A","target":"UBE2D1"},{"source":"ATP6V1C1","target":"VASP"},{"source":"ATP6V1C1","target":"CYRIB"},{"source":"ATP6V1C1","target":"SNX11"},{"source":"ATP6V1C1","target":"MOSPD2"},{"source":"RP2","target":"SNX11"},{"source":"RP2","target":"SIRPA"},{"source":"RP2","target":"XRCC4"},{"source":"AP3B1","target":"AP3S1"},{"source":"AP3B1","target":"AP3M1"},{"source":"AP3B1","target":"AP3D1"},{"source":"AP3B1","target":"PIP4K2C"},{"source":"AP3B1","target":"CLTB"},{"source":"AP3B1","target":"YWHAZ"},{"source":"AP3B1","target":"VTI1B"},{"source":"AP3B1","target":"ARF1"},{"source":"AP3B1","target":"SNX11"},{"source":"AP3B1","target":"KIF5B"},{"source":"AP3B1","target":"ARF6"},{"source":"AP3B1","target":"SEC23B"},{"source":"AP3B1","target":"CLTA"},{"source":"AP3B1","target":"HDAC4"},{"source":"AP3B1","target":"EPB41L3"},{"source":"AP3B1","target":"CAB39"},{"source":"AP3B1","target":"CLINT1"},{"source":"AP3B1","target":"XRCC4"},{"source":"AP3B1","target":"TRIM25"},{"source":"AP3B1","target":"UEVLD"},{"source":"AP3B1","target":"EEA1"},{"source":"AP3B1","target":"PARP4"},{"source":"AP3B1","target":"SNX17"},{"source":"AP3B1","target":"STAM2"},{"source":"ATL3","target":"CCR1"},{"source":"ATL3","target":"ATP6V1C1"},{"source":"ATL3","target":"SPPL2A"},{"source":"ATL3","target":"C18orf32"},{"source":"DNAJC3","target":"SPPL2A"},{"source":"DNAJC3","target":"RP2"},{"source":"DNAJC3","target":"SEC23B"},{"source":"LGALS8","target":"SPPL2A"},{"source":"EMP3","target":"SPPL2A"},{"source":"C18orf32","target":"SPPL2A"},{"source":"SLC9A6","target":"SPPL2A"},{"source":"B4GALT1","target":"SPPL2A"},{"source":"ARF6","target":"KRAS"},{"source":"ARF6","target":"RP2"},{"source":"ARF6","target":"ATP6AP2"},{"source":"ARF6","target":"YWHAZ"},{"source":"ARF6","target":"CLINT1"},{"source":"ATG3","target":"CYRIB"},{"source":"ATG3","target":"GRB2"},{"source":"ATG3","target":"ATP6V1C1"},{"source":"ATG3","target":"RP2"},{"source":"ATP6AP2","target":"ATP6V0D1"},{"source":"ATP6AP2","target":"ATP6V1C1"},{"source":"ATP6AP2","target":"RP2"},{"source":"TRIM25","target":"VASP"},{"source":"TRIM25","target":"UBE2D1"},{"source":"MOSPD2","target":"RP2"},{"source":"EEA1","target":"KIF5B"},{"source":"EEA1","target":"XRCC4"},{"source":"EEA1","target":"GRB2"},{"source":"SEC23B","target":"XRCC4"},{"source":"SEC23B","target":"TRIM25"},{"source":"KRAS","target":"UBE2D1"},{"source":"KRAS","target":"YWHAZ"},{"source":"KRAS","target":"RP2"},{"source":"OSTF1","target":"RP2"},{"source":"OSTF1","target":"VASP"},{"source":"CLTA","target":"EEA1"},{"source":"CLTA","target":"CLTB"},{"source":"ARF1","target":"ARF6"},{"source":"ARF1","target":"KRAS"},{"source":"ARF1","target":"SEC23B"},{"source":"ATP6V0D1","target":"GRB2"},{"source":"ATP6V0D1","target":"RP2"},{"source":"ATP6V0D1","target":"CYRIB"},{"source":"ATP6V0D1","target":"VTI1B"},{"source":"AP3M1","target":"AP3S1"},{"source":"AP3M1","target":"KRAS"},{"source":"AP3M1","target":"STAM2"},{"source":"CAB39","target":"KIF5B"},{"source":"CAB39","target":"PIP4K2C"},{"source":"CAB39","target":"CYRIB"},{"source":"EPB41L3","target":"YWHAZ"},{"source":"STAM2","target":"UBE2D1"},{"source":"NCF2","target":"SIRPA"},{"source":"NCF2","target":"RP2"},{"source":"AP3D1","target":"AP3S1"},{"source":"AP3D1","target":"AP3M1"},{"source":"AP3D1","target":"CLTB"},{"source":"AP3D1","target":"EPB41L3"},{"source":"AP3D1","target":"CLTA"},{"source":"KIF5B","target":"YWHAZ"},{"source":"HDAC4","target":"KIF5B"},{"source":"UEVLD","target":"XRCC4"},{"source":"AP3S1","target":"EPB41L3"},{"source":"CLINT1","target":"CLTA"},{"source":"CLINT1","target":"VTI1B"},{"source":"CLINT1","target":"CLTB"},{"source":"CLINT1","target":"KRAS"},{"source":"NAIP","target":"NCF2"},{"source":"NAIP","target":"SIRPA"},{"source":"NAIP","target":"RP2"},{"source":"CYRIB","target":"OSTF1"},{"source":"CYRIB","target":"TRIM25"},{"source":"CYRIB","target":"VASP"},{"source":"CYRIB","target":"UBE2D1"},{"source":"CYRIB","target":"GRB2"},{"source":"KCTD12","target":"NAIP"},{"source":"KCTD12","target":"NCF2"},{"source":"KCTD12","target":"SIRPA"},{"source":"KCTD12","target":"RP2"}]}