{"nodes":[{"name":"UBE2F"},{"name":"CUL5"},{"name":"DCUN1D1"},{"name":"H2AC14"},{"name":"H2BC3"},{"name":"H2BC10"},{"name":"UBE2D2"},{"name":"NEDD8"},{"name":"UBE2M"},{"name":"CUL2"},{"name":"CAND1"},{"name":"CUL3"},{"name":"H4C2"},{"name":"CUL4B"},{"name":"H4C1"},{"name":"H4C4"},{"name":"COPS2"},{"name":"COPS5"},{"name":"H4C13"},{"name":"RNF7"},{"name":"H4C12"},{"name":"COPS3"},{"name":"H4C5"},{"name":"COPS8"},{"name":"H3C2"},{"name":"H2BC17"},{"name":"H4C8"},{"name":"AGL"},{"name":"H4C3"},{"name":"H4C6"},{"name":"H2AC4"},{"name":"ARIH2"},{"name":"H4C11"},{"name":"H4C15"},{"name":"H2BC6"},{"name":"H3C11"},{"name":"BRD4"},{"name":"H3C7"},{"name":"UBE2D3"},{"name":"H2AC8"},{"name":"H3C3"},{"name":"H2BC7"},{"name":"MCM2"},{"name":"MCM5"},{"name":"YWHAE"},{"name":"H4C14"},{"name":"H4-16"},{"name":"HNRNPK"},{"name":"PSMD3"},{"name":"H3C10"},{"name":"H2BC14"}],"edges":[{"source":"CUL5","target":"RNF7"},{"source":"CUL5","target":"DCUN1D1"},{"source":"CUL5","target":"UBE2M"},{"source":"CUL5","target":"UBE2F"},{"source":"CUL5","target":"NEDD8"},{"source":"DCUN1D1","target":"NEDD8"},{"source":"DCUN1D1","target":"UBE2M"},{"source":"DCUN1D1","target":"UBE2F"},{"source":"DCUN1D1","target":"HNRNPK"},{"source":"DCUN1D1","target":"YWHAE"},{"source":"DCUN1D1","target":"UBE2D3"},{"source":"DCUN1D1","target":"PSMD3"},{"source":"H2AC14","target":"H4C4"},{"source":"H2AC14","target":"H4C8"},{"source":"H2AC14","target":"H4C13"},{"source":"H2AC14","target":"H2BC14"},{"source":"H2AC14","target":"H4C3"},{"source":"H2AC14","target":"H4C1"},{"source":"H2AC14","target":"H4C12"},{"source":"H2AC14","target":"H4C15"},{"source":"H2AC14","target":"H4C2"},{"source":"H2AC14","target":"H4C5"},{"source":"H2AC14","target":"H4C11"},{"source":"H2AC14","target":"H3C3"},{"source":"H2AC14","target":"H4C6"},{"source":"H2AC14","target":"H2AC4"},{"source":"H2AC14","target":"H3C10"},{"source":"H2AC14","target":"MCM5"},{"source":"H2AC14","target":"H2BC6"},{"source":"H2AC14","target":"MCM2"},{"source":"H2AC14","target":"H2BC17"},{"source":"H2AC14","target":"H4-16"},{"source":"H2AC14","target":"H2BC7"},{"source":"H2AC14","target":"H4C14"},{"source":"H2AC14","target":"H2BC3"},{"source":"H2AC14","target":"H3C11"},{"source":"H2AC14","target":"UBE2F"},{"source":"H2AC14","target":"H3C2"},{"source":"H2AC14","target":"H2AC8"},{"source":"H2BC3","target":"H3C3"},{"source":"H2BC3","target":"H4C4"},{"source":"H2BC3","target":"H4C13"},{"source":"H2BC3","target":"H3C7"},{"source":"H2BC3","target":"H3C10"},{"source":"H2BC3","target":"H4C8"},{"source":"H2BC3","target":"H4C6"},{"source":"H2BC3","target":"H4C15"},{"source":"H2BC3","target":"H4C1"},{"source":"H2BC3","target":"H3C11"},{"source":"H2BC3","target":"H3C2"},{"source":"H2BC3","target":"H4C3"},{"source":"H2BC3","target":"H4C12"},{"source":"H2BC3","target":"H4C2"},{"source":"H2BC3","target":"H4C11"},{"source":"H2BC3","target":"H4C5"},{"source":"H2BC3","target":"MCM5"},{"source":"H2BC3","target":"H4-16"},{"source":"H2BC3","target":"H4C14"},{"source":"H2BC3","target":"UBE2F"},{"source":"H2BC3","target":"MCM2"},{"source":"H2BC3","target":"H2BC6"},{"source":"H2BC10","target":"H4C6"},{"source":"H2BC10","target":"H4C4"},{"source":"H2BC10","target":"H4C8"},{"source":"H2BC10","target":"H4C13"},{"source":"H2BC10","target":"H4C12"},{"source":"H2BC10","target":"H4C1"},{"source":"H2BC10","target":"H4C11"},{"source":"H2BC10","target":"H4C5"},{"source":"H2BC10","target":"H2BC17"},{"source":"H2BC10","target":"H4C2"},{"source":"H2BC10","target":"H4C3"},{"source":"H2BC10","target":"H4C15"},{"source":"H2BC10","target":"H4-16"},{"source":"H2BC10","target":"H2BC14"},{"source":"H2BC10","target":"MCM5"},{"source":"H2BC10","target":"H3C7"},{"source":"H2BC10","target":"UBE2F"},{"source":"H2BC10","target":"MCM2"},{"source":"H2BC10","target":"H2BC6"},{"source":"UBE2D2","target":"UBE2F"},{"source":"NEDD8","target":"UBE2M"},{"source":"NEDD8","target":"YWHAE"},{"source":"NEDD8","target":"UBE2D2"},{"source":"NEDD8","target":"UBE2D3"},{"source":"UBE2M","target":"YWHAE"},{"source":"CUL2","target":"CUL3"},{"source":"CUL2","target":"CUL5"},{"source":"CUL2","target":"DCUN1D1"},{"source":"CUL2","target":"PSMD3"},{"source":"CAND1","target":"CUL3"},{"source":"CAND1","target":"CUL2"},{"source":"CAND1","target":"CUL5"},{"source":"CAND1","target":"CUL4B"},{"source":"CAND1","target":"DCUN1D1"},{"source":"CAND1","target":"YWHAE"},{"source":"CAND1","target":"HNRNPK"},{"source":"CAND1","target":"UBE2M"},{"source":"CAND1","target":"COPS5"},{"source":"CUL3","target":"YWHAE"},{"source":"CUL3","target":"DCUN1D1"},{"source":"CUL3","target":"CUL5"},{"source":"CUL3","target":"UBE2M"},{"source":"CUL3","target":"HNRNPK"},{"source":"H4C2","target":"H4C3"},{"source":"H4C2","target":"H4C8"},{"source":"H4C2","target":"HNRNPK"},{"source":"H4C2","target":"H4C4"},{"source":"H4C2","target":"H4C5"},{"source":"H4C2","target":"H4C6"},{"source":"H4C2","target":"MCM5"},{"source":"H4C2","target":"YWHAE"},{"source":"H4C2","target":"MCM2"},{"source":"CUL4B","target":"CUL5"},{"source":"CUL4B","target":"HNRNPK"},{"source":"CUL4B","target":"DCUN1D1"},{"source":"H4C1","target":"H4C3"},{"source":"H4C1","target":"H4C15"},{"source":"H4C1","target":"H4C8"},{"source":"H4C1","target":"H4C13"},{"source":"H4C1","target":"H4C4"},{"source":"H4C1","target":"H4C2"},{"source":"H4C1","target":"H4C5"},{"source":"H4C1","target":"H4C12"},{"source":"H4C1","target":"H4C11"},{"source":"H4C1","target":"H4C14"},{"source":"H4C1","target":"H4C6"},{"source":"H4C1","target":"MCM5"},{"source":"H4C1","target":"HNRNPK"},{"source":"H4C1","target":"MCM2"},{"source":"H4C4","target":"H4C8"},{"source":"H4C4","target":"H4C6"},{"source":"H4C4","target":"H4C5"},{"source":"H4C4","target":"MCM5"},{"source":"H4C4","target":"YWHAE"},{"source":"H4C4","target":"MCM2"},{"source":"COPS2","target":"COPS3"},{"source":"COPS2","target":"COPS5"},{"source":"COPS2","target":"COPS8"},{"source":"COPS2","target":"UBE2M"},{"source":"COPS2","target":"CUL2"},{"source":"COPS2","target":"CUL3"},{"source":"COPS2","target":"CUL5"},{"source":"COPS2","target":"DCUN1D1"},{"source":"COPS2","target":"CUL4B"},{"source":"COPS2","target":"PSMD3"},{"source":"COPS5","target":"COPS8"},{"source":"COPS5","target":"UBE2M"},{"source":"COPS5","target":"DCUN1D1"},{"source":"COPS5","target":"NEDD8"},{"source":"COPS5","target":"CUL5"},{"source":"COPS5","target":"HNRNPK"},{"source":"COPS5","target":"CUL2"},{"source":"H4C13","target":"H4C2"},{"source":"H4C13","target":"H4C8"},{"source":"H4C13","target":"H4C4"},{"source":"H4C13","target":"H4C3"},{"source":"H4C13","target":"H4C5"},{"source":"H4C13","target":"H4C6"},{"source":"H4C13","target":"H4C15"},{"source":"H4C13","target":"MCM5"},{"source":"H4C13","target":"MCM2"},{"source":"H4C13","target":"H4C14"},{"source":"RNF7","target":"UBE2D2"},{"source":"RNF7","target":"UBE2D3"},{"source":"H4C12","target":"H4C5"},{"source":"H4C12","target":"H4C3"},{"source":"H4C12","target":"H4C8"},{"source":"H4C12","target":"H4C2"},{"source":"H4C12","target":"H4C4"},{"source":"H4C12","target":"H4C14"},{"source":"H4C12","target":"H4C6"},{"source":"H4C12","target":"H4C15"},{"source":"H4C12","target":"H4C13"},{"source":"H4C12","target":"MCM5"},{"source":"H4C12","target":"MCM2"},{"source":"COPS3","target":"COPS8"},{"source":"COPS3","target":"COPS5"},{"source":"COPS3","target":"CUL2"},{"source":"COPS3","target":"CUL3"},{"source":"COPS3","target":"UBE2M"},{"source":"COPS3","target":"H3C2"},{"source":"COPS3","target":"YWHAE"},{"source":"COPS3","target":"CUL5"},{"source":"COPS3","target":"H2AC4"},{"source":"COPS3","target":"H2BC17"},{"source":"COPS3","target":"H4C2"},{"source":"COPS3","target":"DCUN1D1"},{"source":"COPS3","target":"H3C7"},{"source":"COPS3","target":"H3C11"},{"source":"COPS3","target":"H4C5"},{"source":"COPS3","target":"NEDD8"},{"source":"COPS3","target":"H2BC7"},{"source":"H4C5","target":"H4C8"},{"source":"H4C5","target":"H4C6"},{"source":"H4C5","target":"MCM5"},{"source":"H4C5","target":"MCM2"},{"source":"COPS8","target":"CUL3"},{"source":"COPS8","target":"CUL2"},{"source":"COPS8","target":"CUL4B"},{"source":"COPS8","target":"NEDD8"},{"source":"COPS8","target":"UBE2M"},{"source":"COPS8","target":"CUL5"},{"source":"COPS8","target":"YWHAE"},{"source":"COPS8","target":"DCUN1D1"},{"source":"H3C2","target":"H3C3"},{"source":"H3C2","target":"H4C1"},{"source":"H3C2","target":"H4C15"},{"source":"H3C2","target":"H4C8"},{"source":"H3C2","target":"H4C6"},{"source":"H3C2","target":"H4C3"},{"source":"H3C2","target":"H4C11"},{"source":"H3C2","target":"H4C4"},{"source":"H3C2","target":"H4C5"},{"source":"H3C2","target":"H4C2"},{"source":"H3C2","target":"H4C13"},{"source":"H3C2","target":"H4C12"},{"source":"H3C2","target":"H3C7"},{"source":"H3C2","target":"H4C14"},{"source":"H3C2","target":"MCM5"},{"source":"H3C2","target":"MCM2"},{"source":"H3C2","target":"UBE2M"},{"source":"H3C2","target":"H4-16"},{"source":"H2BC17","target":"H4C3"},{"source":"H2BC17","target":"H2BC7"},{"source":"H2BC17","target":"H4C8"},{"source":"H2BC17","target":"H4C12"},{"source":"H2BC17","target":"H4C11"},{"source":"H2BC17","target":"H4C13"},{"source":"H2BC17","target":"H4C1"},{"source":"H2BC17","target":"H4C2"},{"source":"H2BC17","target":"H4C6"},{"source":"H2BC17","target":"H4C5"},{"source":"H2BC17","target":"MCM5"},{"source":"H2BC17","target":"H2BC3"},{"source":"H2BC17","target":"H4C4"},{"source":"H2BC17","target":"H2BC6"},{"source":"H2BC17","target":"H4C15"},{"source":"H2BC17","target":"MCM2"},{"source":"H2BC17","target":"H3C10"},{"source":"H2BC17","target":"H4C14"},{"source":"H2BC17","target":"H4-16"},{"source":"H4C8","target":"MCM5"},{"source":"H4C8","target":"MCM2"},{"source":"H4C8","target":"HNRNPK"},{"source":"AGL","target":"DCUN1D1"},{"source":"AGL","target":"CUL5"},{"source":"AGL","target":"CUL4B"},{"source":"H4C3","target":"H4C8"},{"source":"H4C3","target":"H4C5"},{"source":"H4C3","target":"H4C4"},{"source":"H4C3","target":"H4C6"},{"source":"H4C3","target":"MCM5"},{"source":"H4C3","target":"MCM2"},{"source":"H4C6","target":"MCM5"},{"source":"H4C6","target":"H4C8"},{"source":"H4C6","target":"MCM2"},{"source":"H2AC4","target":"H4C2"},{"source":"H2AC4","target":"H3C3"},{"source":"H2AC4","target":"H2BC17"},{"source":"H2AC4","target":"H3C2"},{"source":"H2AC4","target":"H4C13"},{"source":"H2AC4","target":"H4C8"},{"source":"H2AC4","target":"H3C10"},{"source":"H2AC4","target":"H4C1"},{"source":"H2AC4","target":"H3C11"},{"source":"H2AC4","target":"H3C7"},{"source":"H2AC4","target":"H2BC3"},{"source":"H2AC4","target":"H4C11"},{"source":"H2AC4","target":"H4C3"},{"source":"H2AC4","target":"H4C4"},{"source":"H2AC4","target":"H4C15"},{"source":"H2AC4","target":"H2BC14"},{"source":"H2AC4","target":"H4C5"},{"source":"H2AC4","target":"H4C6"},{"source":"H2AC4","target":"H4C12"},{"source":"H2AC4","target":"H4C14"},{"source":"H2AC4","target":"MCM5"},{"source":"H2AC4","target":"MCM2"},{"source":"H2AC4","target":"H2BC7"},{"source":"H2AC4","target":"H4-16"},{"source":"ARIH2","target":"CUL5"},{"source":"ARIH2","target":"BRD4"},{"source":"ARIH2","target":"CAND1"},{"source":"ARIH2","target":"H4C12"},{"source":"ARIH2","target":"UBE2D2"},{"source":"ARIH2","target":"UBE2M"},{"source":"ARIH2","target":"HNRNPK"},{"source":"ARIH2","target":"H4C8"},{"source":"H4C11","target":"H4C3"},{"source":"H4C11","target":"H4C12"},{"source":"H4C11","target":"H4C2"},{"source":"H4C11","target":"H4C5"},{"source":"H4C11","target":"H4C8"},{"source":"H4C11","target":"H4C13"},{"source":"H4C11","target":"H4C4"},{"source":"H4C11","target":"H4C6"},{"source":"H4C11","target":"H4C15"},{"source":"H4C11","target":"H4C14"},{"source":"H4C11","target":"MCM5"},{"source":"H4C15","target":"H4C2"},{"source":"H4C15","target":"H4C8"},{"source":"H4C15","target":"H4C5"},{"source":"H4C15","target":"H4C3"},{"source":"H4C15","target":"H4C4"},{"source":"H4C15","target":"H4C6"},{"source":"H4C15","target":"MCM2"},{"source":"H4C15","target":"MCM5"},{"source":"H2BC6","target":"H4C8"},{"source":"H2BC6","target":"H4C13"},{"source":"H2BC6","target":"H4C12"},{"source":"H2BC6","target":"H4C5"},{"source":"H2BC6","target":"H4C4"},{"source":"H2BC6","target":"H4C3"},{"source":"H2BC6","target":"H4C2"},{"source":"H2BC6","target":"H4C6"},{"source":"H2BC6","target":"H4C11"},{"source":"H2BC6","target":"H4C1"},{"source":"H2BC6","target":"H4C15"},{"source":"H2BC6","target":"MCM5"},{"source":"H2BC6","target":"H2BC7"},{"source":"H2BC6","target":"H3C10"},{"source":"H2BC6","target":"H4-16"},{"source":"H2BC6","target":"H3C7"},{"source":"H2BC6","target":"H4C14"},{"source":"H2BC6","target":"MCM2"},{"source":"H2BC6","target":"H3C3"},{"source":"H3C11","target":"H4C13"},{"source":"H3C11","target":"H4C11"},{"source":"H3C11","target":"H4C15"},{"source":"H3C11","target":"H3C2"},{"source":"H3C11","target":"H4C12"},{"source":"H3C11","target":"H4C2"},{"source":"H3C11","target":"H4C5"},{"source":"H3C11","target":"H3C3"},{"source":"H3C11","target":"H3C7"},{"source":"H3C11","target":"H4C3"},{"source":"H3C11","target":"H4C1"},{"source":"H3C11","target":"H4C4"},{"source":"H3C11","target":"MCM5"},{"source":"H3C11","target":"H4C8"},{"source":"H3C11","target":"H4C6"},{"source":"H3C11","target":"MCM2"},{"source":"H3C11","target":"H4C14"},{"source":"H3C11","target":"H4-16"},{"source":"BRD4","target":"UBE2D2"},{"source":"BRD4","target":"H3C2"},{"source":"BRD4","target":"H2AC14"},{"source":"BRD4","target":"H2BC7"},{"source":"BRD4","target":"H3C3"},{"source":"BRD4","target":"HNRNPK"},{"source":"BRD4","target":"H3C11"},{"source":"H3C7","target":"H4C8"},{"source":"H3C7","target":"H4C4"},{"source":"H3C7","target":"H4C13"},{"source":"H3C7","target":"H4C11"},{"source":"H3C7","target":"MCM2"},{"source":"H3C7","target":"MCM5"},{"source":"H3C7","target":"H4C5"},{"source":"H3C7","target":"H4C3"},{"source":"H3C7","target":"H4C6"},{"source":"H3C7","target":"H4C2"},{"source":"H3C7","target":"H4C1"},{"source":"H3C7","target":"H4C15"},{"source":"H3C7","target":"H4C12"},{"source":"H3C7","target":"H4C14"},{"source":"H3C7","target":"H4-16"},{"source":"H2AC8","target":"H4C8"},{"source":"H2AC8","target":"H4C5"},{"source":"H2AC8","target":"H3C7"},{"source":"H2AC8","target":"H4C6"},{"source":"H2AC8","target":"H2BC3"},{"source":"H2AC8","target":"H3C10"},{"source":"H2AC8","target":"H4C11"},{"source":"H2AC8","target":"H3C3"},{"source":"H2AC8","target":"H4C1"},{"source":"H2AC8","target":"H4C15"},{"source":"H2AC8","target":"H4C12"},{"source":"H2AC8","target":"H4C2"},{"source":"H2AC8","target":"H4C4"},{"source":"H2AC8","target":"H2BC17"},{"source":"H2AC8","target":"H3C11"},{"source":"H2AC8","target":"H4C3"},{"source":"H2AC8","target":"H2BC14"},{"source":"H2AC8","target":"H3C2"},{"source":"H2AC8","target":"H4C13"},{"source":"H2AC8","target":"H2BC7"},{"source":"H2AC8","target":"H2BC10"},{"source":"H2AC8","target":"H2BC6"},{"source":"H2AC8","target":"MCM5"},{"source":"H2AC8","target":"H4-16"},{"source":"H2AC8","target":"H4C14"},{"source":"H2AC8","target":"MCM2"},{"source":"H3C3","target":"H4C15"},{"source":"H3C3","target":"H4C1"},{"source":"H3C3","target":"H4C4"},{"source":"H3C3","target":"H4C13"},{"source":"H3C3","target":"H4C2"},{"source":"H3C3","target":"H4C8"},{"source":"H3C3","target":"H4C12"},{"source":"H3C3","target":"H4C3"},{"source":"H3C3","target":"H4C6"},{"source":"H3C3","target":"H4C11"},{"source":"H3C3","target":"H4C14"},{"source":"H3C3","target":"H4C5"},{"source":"H3C3","target":"H3C7"},{"source":"H3C3","target":"MCM2"},{"source":"H3C3","target":"MCM5"},{"source":"H3C3","target":"H4-16"},{"source":"H3C3","target":"UBE2M"},{"source":"H2BC7","target":"H4C5"},{"source":"H2BC7","target":"H4C8"},{"source":"H2BC7","target":"H4C11"},{"source":"H2BC7","target":"H4C1"},{"source":"H2BC7","target":"H4C2"},{"source":"H2BC7","target":"H4C12"},{"source":"H2BC7","target":"H4C4"},{"source":"H2BC7","target":"H4C6"},{"source":"H2BC7","target":"H4C15"},{"source":"H2BC7","target":"H4C13"},{"source":"H2BC7","target":"H4C3"},{"source":"H2BC7","target":"MCM5"},{"source":"H2BC7","target":"H3C10"},{"source":"H2BC7","target":"H4C14"},{"source":"H2BC7","target":"MCM2"},{"source":"H2BC7","target":"H4-16"},{"source":"H2BC7","target":"H3C11"},{"source":"H2BC7","target":"H3C2"},{"source":"MCM2","target":"MCM5"},{"source":"H4C14","target":"H4C15"},{"source":"H4C14","target":"H4C5"},{"source":"H4C14","target":"H4C4"},{"source":"H4C14","target":"H4C2"},{"source":"H4C14","target":"H4C8"},{"source":"H4C14","target":"MCM5"},{"source":"H4C14","target":"H4C3"},{"source":"H4C14","target":"H4C6"},{"source":"H4C14","target":"MCM2"},{"source":"H4-16","target":"H4C8"},{"source":"H4-16","target":"H4C12"},{"source":"H4-16","target":"H4C6"},{"source":"H4-16","target":"H4C2"},{"source":"H4-16","target":"H4C5"},{"source":"H4-16","target":"H4C13"},{"source":"H4-16","target":"H4C1"},{"source":"H4-16","target":"H4C4"},{"source":"H4-16","target":"H4C15"},{"source":"H4-16","target":"H4C11"},{"source":"H4-16","target":"H4C3"},{"source":"HNRNPK","target":"NEDD8"},{"source":"HNRNPK","target":"UBE2M"},{"source":"PSMD3","target":"UBE2M"},{"source":"H3C10","target":"H4C12"},{"source":"H3C10","target":"H4C8"},{"source":"H3C10","target":"H4C2"},{"source":"H3C10","target":"H4C5"},{"source":"H3C10","target":"H4C13"},{"source":"H3C10","target":"H3C11"},{"source":"H3C10","target":"H4C11"},{"source":"H3C10","target":"H4C3"},{"source":"H3C10","target":"H4C1"},{"source":"H3C10","target":"H4C4"},{"source":"H3C10","target":"H3C2"},{"source":"H3C10","target":"H3C7"},{"source":"H3C10","target":"H3C3"},{"source":"H3C10","target":"H4C15"},{"source":"H3C10","target":"H4C6"},{"source":"H3C10","target":"H4C14"},{"source":"H3C10","target":"H4-16"},{"source":"H2BC14","target":"H4C4"},{"source":"H2BC14","target":"H4C3"},{"source":"H2BC14","target":"H4C1"},{"source":"H2BC14","target":"H4C15"},{"source":"H2BC14","target":"H4C11"},{"source":"H2BC14","target":"H4C8"},{"source":"H2BC14","target":"H4C13"},{"source":"H2BC14","target":"H4C2"},{"source":"H2BC14","target":"H4C6"},{"source":"H2BC14","target":"H4C5"},{"source":"H2BC14","target":"H4C12"},{"source":"H2BC14","target":"H2BC3"},{"source":"H2BC14","target":"H3C7"},{"source":"H2BC14","target":"MCM2"},{"source":"H2BC14","target":"MCM5"},{"source":"H2BC14","target":"H4C14"},{"source":"H2BC14","target":"H4-16"},{"source":"H2BC14","target":"H2BC7"}]}