{"nodes":[{"name":"WIPI1"},{"name":"OPTN"},{"name":"ATG9A"},{"name":"ATG2A"},{"name":"TNFAIP6"},{"name":"FCAR"},{"name":"ATG2B"},{"name":"WDR45"},{"name":"KCMF1"},{"name":"UBR4"},{"name":"GABARAPL1"},{"name":"GABARAPL2"},{"name":"APP"},{"name":"DNAJB2"},{"name":"EPB41"},{"name":"PTK2"},{"name":"SFXN1"},{"name":"MPP1"},{"name":"ADD2"},{"name":"CDC34"},{"name":"H3C1"},{"name":"RAB3IL1"},{"name":"HSPB1"},{"name":"H2BC7"},{"name":"RNF11"},{"name":"SOD1"},{"name":"PI4K2A"},{"name":"EIF5A2"},{"name":"CLCN3"},{"name":"AP2M1"},{"name":"SYVN1"},{"name":"LGALS3"},{"name":"PIGH"},{"name":"IGF2R"},{"name":"AMFR"},{"name":"AP2A1"},{"name":"SRC"},{"name":"FLCN"},{"name":"MYH9"},{"name":"RNF185"},{"name":"YWHAH"},{"name":"RAB5A"},{"name":"B4GALT5"},{"name":"HERPUD1"},{"name":"TMEM63B"},{"name":"TMBIM1"},{"name":"CALCOCO1"},{"name":"HERC1"},{"name":"BSDC1"},{"name":"DAAM1"},{"name":"DUSP16"}],"edges":[{"source":"OPTN","target":"RAB3IL1"},{"source":"OPTN","target":"SFXN1"},{"source":"OPTN","target":"SOD1"},{"source":"OPTN","target":"WIPI1"},{"source":"OPTN","target":"RNF11"},{"source":"OPTN","target":"PTK2"},{"source":"ATG9A","target":"TMEM63B"},{"source":"ATG9A","target":"LGALS3"},{"source":"ATG9A","target":"WIPI1"},{"source":"ATG9A","target":"MYH9"},{"source":"ATG9A","target":"OPTN"},{"source":"ATG9A","target":"DNAJB2"},{"source":"ATG9A","target":"HERPUD1"},{"source":"ATG9A","target":"CLCN3"},{"source":"ATG9A","target":"PI4K2A"},{"source":"ATG9A","target":"IGF2R"},{"source":"ATG9A","target":"RAB5A"},{"source":"ATG9A","target":"B4GALT5"},{"source":"ATG9A","target":"SRC"},{"source":"ATG9A","target":"SYVN1"},{"source":"ATG9A","target":"PIGH"},{"source":"ATG9A","target":"FLCN"},{"source":"ATG9A","target":"YWHAH"},{"source":"ATG9A","target":"TMBIM1"},{"source":"ATG9A","target":"RNF185"},{"source":"ATG2A","target":"WDR45"},{"source":"ATG2A","target":"ATG2B"},{"source":"ATG2A","target":"GABARAPL1"},{"source":"ATG2A","target":"WIPI1"},{"source":"ATG2A","target":"UBR4"},{"source":"ATG2A","target":"KCMF1"},{"source":"TNFAIP6","target":"WIPI1"},{"source":"FCAR","target":"TNFAIP6"},{"source":"ATG2B","target":"WDR45"},{"source":"ATG2B","target":"OPTN"},{"source":"ATG2B","target":"HERC1"},{"source":"ATG2B","target":"CALCOCO1"},{"source":"ATG2B","target":"DAAM1"},{"source":"ATG2B","target":"DUSP16"},{"source":"KCMF1","target":"UBR4"},{"source":"GABARAPL1","target":"PI4K2A"},{"source":"GABARAPL1","target":"GABARAPL2"},{"source":"GABARAPL2","target":"OPTN"},{"source":"APP","target":"OPTN"},{"source":"APP","target":"PTK2"},{"source":"DNAJB2","target":"WDR45"},{"source":"EPB41","target":"OPTN"},{"source":"EPB41","target":"MPP1"},{"source":"PTK2","target":"SRC"},{"source":"MPP1","target":"OPTN"},{"source":"ADD2","target":"APP"},{"source":"ADD2","target":"OPTN"},{"source":"CDC34","target":"OPTN"},{"source":"H3C1","target":"OPTN"},{"source":"HSPB1","target":"OPTN"},{"source":"H2BC7","target":"OPTN"},{"source":"EIF5A2","target":"OPTN"},{"source":"CLCN3","target":"FLCN"},{"source":"CLCN3","target":"DNAJB2"},{"source":"CLCN3","target":"PIGH"},{"source":"CLCN3","target":"GABARAPL2"},{"source":"AP2M1","target":"MYH9"},{"source":"AP2M1","target":"GABARAPL2"},{"source":"AP2M1","target":"ATG9A"},{"source":"AP2M1","target":"MPP1"},{"source":"LGALS3","target":"TMEM63B"},{"source":"AMFR","target":"RNF185"},{"source":"AMFR","target":"PIGH"},{"source":"AMFR","target":"ATG9A"},{"source":"AMFR","target":"SYVN1"},{"source":"AP2A1","target":"AP2M1"},{"source":"AP2A1","target":"MYH9"},{"source":"AP2A1","target":"ATG9A"},{"source":"AP2A1","target":"GABARAPL2"},{"source":"RNF185","target":"SYVN1"},{"source":"B4GALT5","target":"IGF2R"},{"source":"HERPUD1","target":"SYVN1"},{"source":"CALCOCO1","target":"DAAM1"},{"source":"CALCOCO1","target":"GABARAPL2"},{"source":"CALCOCO1","target":"WDR45"},{"source":"HERC1","target":"KCMF1"},{"source":"HERC1","target":"UBR4"},{"source":"BSDC1","target":"UBR4"},{"source":"BSDC1","target":"CALCOCO1"},{"source":"BSDC1","target":"GABARAPL1"}]}